{"node":{"406570c3471b3c3463f87437da0513e3f84b76d609":{"workers":{"app/view/page":{"moduleId":"10174","async":false},"app/share/page":{"moduleId":"10174","async":false},"app/create/page":{"moduleId":"10174","async":false}},"layer":{"app/view/page":"action-browser","app/share/page":"action-browser","app/create/page":"action-browser"}},"40c4cd7c33da312b6877da2490f15283bef909b37f":{"workers":{"app/view/page":{"moduleId":"10174","async":false},"app/share/page":{"moduleId":"10174","async":false},"app/create/page":{"moduleId":"10174","async":false}},"layer":{"app/view/page":"action-browser","app/share/page":"action-browser","app/create/page":"action-browser"}}},"edge":{},"encryptionKey":"N/by4e91Mlx2IYs2Hsf3eMcW0AwziP/cCsrNoqNUe+I="}